ml_models/__init__.py
ml_models/build_model.py
ml_models/console/console.py
ml_models/driver/main.py
ml_models/evaluate.py
ml_models/hyper_parameter optimization/__init__.py
ml_models/hyper_parameter optimization/knn_grid_search.py
ml_models/hyper_parameter optimization/mlp_grid_search.py
ml_models/hyper_parameter optimization/svm_grid_search.py
ml_models-0.1.7.dist-info/entry_points.txt
ml_models-0.1.7.dist-info/WHEEL
ml_models-0.1.7.dist-info/METADATA
ml_models-0.1.7.dist-info/RECORD
