Metadata-Version: 2.1
Name: ml-models
Version: 0.1.7
Summary:  This project is based upon basic ml-model testing and building a table.
Author: addyR
Author-email: adarsharegmi121@gmail.com
Requires-Python: >=3.8,<4.0
Classifier: Programming Language :: Python :: 3
Classifier: Programming Language :: Python :: 3.8
Classifier: Programming Language :: Python :: 3.9
Requires-Dist: matplotlib (>=3.4.3,<4.0.0)
Requires-Dist: pandas (>=1.3.3,<2.0.0)
Requires-Dist: sklearn (>=0.0,<0.1)
